pycspr/__init__.py
pycspr/api/__init__.py
pycspr/api/constants.py
pycspr/api/rest/__init__.py
pycspr/api/rest/client.py
pycspr/api/rest/connection.py
pycspr/api/rest/proxy.py
pycspr/api/rpc/__init__.py
pycspr/api/rpc/client.py
pycspr/api/rpc/connection.py
pycspr/api/rpc/params.py
pycspr/api/rpc/proxy.py
pycspr/api/rpc_speculative/__init__.py
pycspr/api/rpc_speculative/client.py
pycspr/api/rpc_speculative/connection.py
pycspr/api/rpc_speculative/proxy.py
pycspr/api/sse/__init__.py
pycspr/api/sse/client.py
pycspr/api/sse/connection.py
pycspr/api/sse/proxy.py
pycspr/crypto/__init__.py
pycspr/crypto/checksummer.py
pycspr/crypto/cl_operations.py
pycspr/crypto/ecc.py
pycspr/crypto/ecc_ed25519.py
pycspr/crypto/ecc_secp256k1.py
pycspr/crypto/hashifier.py
pycspr/crypto/hashifier_blake2b.py
pycspr/crypto/hashifier_blake3.py
pycspr/factory/__init__.py
pycspr/factory/accounts.py
pycspr/factory/deploys.py
pycspr/factory/digests.py
pycspr/serializer/__init__.py
pycspr/serializer/binary/__init__.py
pycspr/serializer/binary/cl_type/__init__.py
pycspr/serializer/binary/cl_type/decoder.py
pycspr/serializer/binary/cl_type/encoder.py
pycspr/serializer/binary/cl_value/__init__.py
pycspr/serializer/binary/cl_value/decoder.py
pycspr/serializer/binary/cl_value/encoder.py
pycspr/serializer/binary/node_rpc/__init__.py
pycspr/serializer/binary/node_rpc/decoder.py
pycspr/serializer/binary/node_rpc/encoder.py
pycspr/serializer/json/__init__.py
pycspr/serializer/json/cl_type/__init__.py
pycspr/serializer/json/cl_type/decoder.py
pycspr/serializer/json/cl_type/encoder.py
pycspr/serializer/json/cl_value/__init__.py
pycspr/serializer/json/cl_value/decoder.py
pycspr/serializer/json/cl_value/encoder.py
pycspr/serializer/json/node_rpc/__init__.py
pycspr/serializer/json/node_rpc/decoder.py
pycspr/serializer/json/node_rpc/encoder.py
pycspr/serializer/utils/__init__.py
pycspr/serializer/utils/cl_value_to_cl_type.py
pycspr/serializer/utils/cl_value_to_parsed.py
pycspr/types/__init__.py
pycspr-1.2.0.dist-info/LICENSE
pycspr-1.2.0.dist-info/METADATA
pycspr-1.2.0.dist-info/WHEEL
pycspr-1.2.0.dist-info/RECORD
