Metadata-Version: 2.1
Name: pycspr
Version: 1.2.0
Summary: Python library for interacting with a CSPR node.
Home-page: https://github.com/casper-network/casper-python-sdk
License: Apache-2.0
Keywords: Casper Network,Blockchain,Python
Author: Mark A. Greenslade
Author-email: asladeofgreen@gmail.com
Maintainer: Mark A. Greenslade
Maintainer-email: asladeofgreen@gmail.com
Requires-Python: >=3.12,<4.0
Classifier: Development Status :: 4 - Beta
Classifier: Intended Audience :: Developers
Classifier: License :: OSI Approved :: Apache Software License
Classifier: Natural Language :: English
Classifier: Operating System :: OS Independent
Classifier: Programming Language :: Python
Classifier: Programming Language :: Python :: 3
Classifier: Programming Language :: Python :: 3.12
Classifier: Topic :: Software Development :: Libraries :: Python Modules
Requires-Dist: blake3 (>=0.4.1,<0.5.0)
Requires-Dist: cryptography (>=42.0.2,<43.0.0)
Requires-Dist: ecdsa (>=0.18.0,<0.19.0)
Requires-Dist: jsonrpcclient (>=4.0.3,<5.0.0)
Requires-Dist: requests (>=2.31.0,<3.0.0)
Requires-Dist: sseclient-py (>=1.8.0,<2.0.0)
Project-URL: Documentation, https://github.com/casper-network/casper-python-sdk/blob/main/README.md
Project-URL: Repository, https://github.com/casper-network/casper-python-sdk
